{
  "generic": {
    "type": "generic_trumon_windshield",
    "mustBeRemovedByScrewdriver": true,
    "forwardsDamageMultiplier": 0.0,
    "destroyable": true,
    "width": 0.1,
    "height": 0.1
  },
  "parts": [],
  "collisionGroups": [
    {
      "applyAfter": "body_windshield_rotatable",
      "collisionTypes": [
        "entity",
        "click"
      ],
      "collisions": [
        {
          "pos": [
            -0.46875,
            0.65625,
            0.0
          ],
          "width": 0.25,
          "height": 0.1875,
          "variableName": "door_windshield",
          "variableType": "toggle"
        },
        {
          "pos": [
            0.46875,
            0.65625,
            0.0
          ],
          "width": 0.25,
          "height": 0.1875,
          "variableName": "door_windshield",
          "variableType": "toggle"
        },
        {
          "pos": [
            0.0,
            0.65625,
            0.0
          ],
          "width": 0.25,
          "height": 0.1875,
          "variableName": "door_windshield",
          "variableType": "toggle"
        }
      ]
    },
    {
      "applyAfter": "body_windshield_rotatable",
      "collisionTypes": [
        "attack",
        "vehicle",
        "entity",
        "click"
      ],
      "collisions": [
        {
          "pos": [
            0.125,
            1.15625,
            0.0
          ],
          "width": 0.125,
          "height": 0.0625
        },
        {
          "pos": [
            0.625,
            1.15625,
            0.0
          ],
          "width": 0.125,
          "height": 0.0625
        },
        {
          "pos": [
            0.375,
            1.15625,
            0.0
          ],
          "width": 0.125,
          "height": 0.0625
        },
        {
          "pos": [
            -0.6875,
            0.65625,
            0.0
          ],
          "width": 0.125,
          "height": 0.0625
        },
        {
          "pos": [
            -0.125,
            1.15625,
            0.0
          ],
          "width": 0.125,
          "height": 0.0625
        },
        {
          "pos": [
            -0.375,
            1.15625,
            0.0
          ],
          "width": 0.125,
          "height": 0.0625
        },
        {
          "pos": [
            -0.625,
            1.15625,
            0.0
          ],
          "width": 0.125,
          "height": 0.0625
        },
        {
          "pos": [
            0.6875,
            0.65625,
            0.0
          ],
          "width": 0.125,
          "height": 0.0625
        },
        {
          "pos": [
            -0.125,
            0.65625,
            0.0
          ],
          "width": 0.125,
          "height": 0.0625
        },
        {
          "pos": [
            -0.5,
            0.65625,
            0.0
          ],
          "width": 0.125,
          "height": 0.0625
        },
        {
          "pos": [
            -0.3125,
            0.65625,
            0.0
          ],
          "width": 0.125,
          "height": 0.0625
        },
        {
          "pos": [
            0.5,
            0.65625,
            0.0
          ],
          "width": 0.125,
          "height": 0.0625
        },
        {
          "pos": [
            0.125,
            0.65625,
            0.0
          ],
          "width": 0.125,
          "height": 0.0625
        },
        {
          "pos": [
            0.3125,
            0.65625,
            0.0
          ],
          "width": 0.125,
          "height": 0.0625
        }
      ]
    },
    {
      "collisionTypes": [
        "attack",
        "vehicle",
        "entity"
      ],
      "collisions": [
        {
          "pos": [
            -0.125,
            0.09375,
            0.0
          ],
          "width": 0.125,
          "height": 0.0625
        },
        {
          "pos": [
            0.625,
            0.09375,
            0.0
          ],
          "width": 0.125,
          "height": 0.0625
        },
        {
          "pos": [
            -0.375,
            0.09375,
            0.0
          ],
          "width": 0.125,
          "height": 0.0625
        },
        {
          "pos": [
            -0.625,
            0.09375,
            0.0
          ],
          "width": 0.125,
          "height": 0.0625
        },
        {
          "pos": [
            0.125,
            0.09375,
            0.0
          ],
          "width": 0.125,
          "height": 0.0625
        },
        {
          "pos": [
            0.125,
            0.59375,
            0.0
          ],
          "width": 0.125,
          "height": 0.0625
        },
        {
          "pos": [
            -0.375,
            0.59375,
            0.0
          ],
          "width": 0.125,
          "height": 0.0625
        },
        {
          "pos": [
            -0.125,
            0.59375,
            0.0
          ],
          "width": 0.125,
          "height": 0.0625
        },
        {
          "pos": [
            -0.625,
            0.59375,
            0.0
          ],
          "width": 0.125,
          "height": 0.0625
        },
        {
          "pos": [
            0.625,
            0.59375,
            0.0
          ],
          "width": 0.125,
          "height": 0.0625
        },
        {
          "pos": [
            0.375,
            0.59375,
            0.0
          ],
          "width": 0.125,
          "height": 0.0625
        },
        {
          "pos": [
            0.625,
            1.21875,
            0.0
          ],
          "width": 0.125,
          "height": 0.0625
        },
        {
          "pos": [
            0.125,
            1.21875,
            0.0
          ],
          "width": 0.125,
          "height": 0.0625
        },
        {
          "pos": [
            0.375,
            0.09375,
            0.0
          ],
          "width": 0.125,
          "height": 0.0625
        },
        {
          "pos": [
            -0.625,
            1.21875,
            0.0
          ],
          "width": 0.125,
          "height": 0.0625
        },
        {
          "pos": [
            -0.375,
            1.21875,
            0.0
          ],
          "width": 0.125,
          "height": 0.0625
        },
        {
          "pos": [
            -0.875,
            0.65625,
            0.0
          ],
          "width": 0.125,
          "height": 1.1875
        },
        {
          "pos": [
            -0.125,
            1.21875,
            0.0
          ],
          "width": 0.125,
          "height": 0.0625
        },
        {
          "pos": [
            0.375,
            1.21875,
            0.0
          ],
          "width": 0.125,
          "height": 0.0625
        },
        {
          "pos": [
            0.875,
            0.65625,
            0.0
          ],
          "width": 0.125,
          "height": 1.1875
        }
      ]
    }
  ],
  "definitions": [
    {
      "subName": "",
      "useVehicleTexture": true,
      "modelName": "part_trumon_windshield",
      "benchTexture": "part_trumon_windshield",
      "name": "Trin Trumon Windshield",
      "extraMaterialLists": [
        [
          "minecraft:glass_pane:0:3"
        ]
      ]
    }
  ],
  "rendering": {
    "animatedObjects": [
      {
        "objectName": "body_windshield_rotatable",
        "animations": [
          {
            "animationType": "rotation",
            "variable": "door_windshield",
            "centerPoint": [
              0.0,
              1.09375,
              0.0
            ],
            "axis": [
              25.0,
              0.0,
              0.0
            ],
            "duration": 15,
            "forwardsEasing": "easeoutback",
            "reverseEasing": "easeincubic",
            "forwardsStartSound": "iv_tpp:bootopen",
            "reverseEndSound": "iv_tpp:bootclose"
          }
        ]
      },
      {
        "objectName": "body_windshield_rotatable_window",
        "applyAfter": "body_windshield_rotatable",
        "animations": []
      }
    ],
    "lightObjects": [],
    "particles": [],
    "modelType": "obj"
  },
  "general": {
    "health": 100,
    "materialLists": [
      [
        "minecraft:iron_ingot:0:15"
      ]
    ]
  }
}